YOLOv8_Explainer/__init__.py
YOLOv8_Explainer/core.py
YOLOv8_Explainer/utils.py
YOLOv8_Explainer-0.0.5.dist-info/LICENSE
YOLOv8_Explainer-0.0.5.dist-info/METADATA
YOLOv8_Explainer-0.0.5.dist-info/WHEEL
YOLOv8_Explainer-0.0.5.dist-info/top_level.txt
YOLOv8_Explainer-0.0.5.dist-info/RECORD
